{
  "query023_multi": {
    "query_id": "query023_multi",
    "variants": [
      {
        "name": "V1: Original SQL",
        "avg_ms": 1570.99,
        "rows": 1,
        "times": [
          2010.77,
          1597.81,
          1590.93,
          1515.1,
          1524.22
        ]
      },
      {
        "name": "V2: Original + no_hashjoin+max_parallel",
        "avg_ms": 1508.41,
        "rows": 1,
        "times": [
          1480.15,
          1514.43,
          1501.12,
          1509.68,
          1544.42
        ]
      },
      {
        "name": "V3: Rewrite (worker_4_sql.sql)",
        "avg_ms": 1501.47,
        "rows": 1,
        "times": [
          1504.67,
          1511.27,
          1479.86,
          1492.99,
          1506.74
        ]
      },
      {
        "name": "V4: Rewrite + no_hashjoin+max_parallel",
        "avg_ms": 1471.06,
        "rows": 1,
        "times": [
          1448.05,
          1475.9,
          1461.94,
          1475.33,
          1488.19
        ]
      },
      {
        "name": "V5: Rewrite + work_mem_256mb",
        "avg_ms": 1484.87,
        "rows": 1,
        "times": [
          1444.27,
          1441.51,
          1484.84,
          1525.51,
          1563.86
        ]
      },
      {
        "name": "V5: Rewrite + ssd_costs",
        "avg_ms": 1513.92,
        "rows": 1,
        "times": [
          1484.91,
          1502.67,
          1512.99,
          1537.91,
          1526.09
        ]
      },
      {
        "name": "V5: Rewrite + ssd_plus_mem",
        "avg_ms": 1473.64,
        "rows": 1,
        "times": [
          1523.1,
          1440.95,
          1479.69,
          1471.59,
          1469.64
        ]
      },
      {
        "name": "V5: Rewrite + max_parallel",
        "avg_ms": 1437.88,
        "rows": 1,
        "times": [
          1445.53,
          1447.44,
          1395.71,
          1420.69,
          1466.55
        ]
      },
      {
        "name": "V5: Rewrite + no_jit",
        "avg_ms": 1494.57,
        "rows": 1,
        "times": [
          1508.27,
          1489.53,
          1498.54,
          1474.26,
          1495.66
        ]
      },
      {
        "name": "V5: Rewrite + force_hash",
        "avg_ms": 5737.33,
        "rows": 1,
        "times": [
          5935.01,
          5680.05,
          5552.58,
          5713.88,
          5818.06
        ]
      },
      {
        "name": "V5: Rewrite + no_nestloop",
        "avg_ms": 6403.0,
        "rows": 1,
        "times": [
          6070.07,
          6223.77,
          6687.14,
          7557.94,
          6298.09
        ]
      },
      {
        "name": "V5: Rewrite + no_parallel",
        "avg_ms": 2037.39,
        "rows": 1,
        "times": [
          2083.66,
          2082.5,
          2000.51,
          2018.69,
          2010.97
        ]
      },
      {
        "name": "V5: Rewrite + no_jit+ssd",
        "avg_ms": 1477.57,
        "rows": 1,
        "times": [
          1464.9,
          1448.68,
          1485.94,
          1481.86,
          1520.17
        ]
      },
      {
        "name": "V5: Rewrite + mem_256mb+max_par",
        "avg_ms": 1445.16,
        "rows": 1,
        "times": [
          1464.6,
          1462.34,
          1455.57,
          1417.57,
          1396.98
        ]
      }
    ]
  },
  "query083_multi": {
    "query_id": "query083_multi",
    "variants": [
      {
        "name": "V1: Original SQL",
        "avg_ms": 142.71,
        "rows": 0,
        "times": [
          184.81,
          146.39,
          144.21,
          137.52,
          137.45
        ]
      },
      {
        "name": "V2: Original + force_nestloop+ssd_costs",
        "avg_ms": 146.77,
        "rows": 0,
        "times": [
          388.87,
          149.64,
          143.24,
          142.56,
          147.43
        ]
      },
      {
        "name": "V3: Rewrite (worker_2_sql.sql)",
        "avg_ms": 287.36,
        "rows": 0,
        "times": [
          283.39,
          298.54,
          290.15,
          277.25,
          288.55
        ]
      },
      {
        "name": "V4: Rewrite + force_nestloop+ssd_costs",
        "avg_ms": 20.43,
        "rows": 0,
        "times": [
          35.78,
          32.67,
          15.51,
          13.02,
          13.11
        ]
      },
      {
        "name": "V5: Rewrite + work_mem_256mb",
        "avg_ms": 277.99,
        "rows": 0,
        "times": [
          279.68,
          277.53,
          293.92,
          276.33,
          276.77
        ]
      },
      {
        "name": "V5: Rewrite + ssd_costs",
        "avg_ms": 205.35,
        "rows": 0,
        "times": [
          208.55,
          211.96,
          203.92,
          201.32,
          203.59
        ]
      },
      {
        "name": "V5: Rewrite + ssd_plus_mem",
        "avg_ms": 204.73,
        "rows": 0,
        "times": [
          208.38,
          214.83,
          202.11,
          203.71,
          199.74
        ]
      },
      {
        "name": "V5: Rewrite + max_parallel",
        "avg_ms": 256.69,
        "rows": 0,
        "times": [
          253.66,
          260.99,
          250.61,
          255.41,
          262.49
        ]
      },
      {
        "name": "V5: Rewrite + no_jit",
        "avg_ms": 289.14,
        "rows": 0,
        "times": [
          294.59,
          279.9,
          285.1,
          297.34,
          287.73
        ]
      },
      {
        "name": "V5: Rewrite + force_hash",
        "avg_ms": 74.44,
        "rows": 0,
        "times": [
          299.19,
          76.11,
          71.12,
          69.43,
          76.1
        ]
      },
      {
        "name": "V5: Rewrite + no_nestloop",
        "avg_ms": 380.49,
        "rows": 0,
        "times": [
          747.19,
          388.49,
          373.81,
          370.37,
          379.18
        ]
      },
      {
        "name": "V5: Rewrite + no_parallel",
        "avg_ms": 463.57,
        "rows": 0,
        "times": [
          464.32,
          470.08,
          456.3,
          470.11,
          448.55
        ]
      },
      {
        "name": "V5: Rewrite + no_jit+ssd",
        "avg_ms": 221.66,
        "rows": 0,
        "times": [
          223.56,
          220.96,
          223.73,
          220.46,
          214.55
        ]
      },
      {
        "name": "V5: Rewrite + mem_256mb+max_par",
        "avg_ms": 268.51,
        "rows": 0,
        "times": [
          259.93,
          273.08,
          268.47,
          263.99,
          275.85
        ]
      }
    ]
  },
  "query014_multi": {
    "query_id": "query014_multi",
    "variants": [
      {
        "name": "V1: Original SQL",
        "avg_ms": 12049.72,
        "rows": 67,
        "times": [
          14879.9,
          12057.75,
          12185.41,
          11695.35,
          11906.0
        ]
      },
      {
        "name": "V2: Original + no_hashjoin+ssd_costs",
        "avg_ms": 11220.5,
        "rows": 67,
        "times": [
          11536.58,
          11228.63,
          11074.6,
          10766.45,
          11358.27
        ]
      },
      {
        "name": "V3: Rewrite (worker_4_sql.sql)",
        "avg_ms": 18346.57,
        "rows": 67,
        "times": [
          18650.22,
          19583.81,
          18213.63,
          18175.86,
          17949.18
        ]
      },
      {
        "name": "V4: Rewrite + no_hashjoin+ssd_costs",
        "avg_ms": 13499.86,
        "rows": 67,
        "times": [
          15188.42,
          13481.79,
          13281.99,
          13316.57,
          13701.21
        ]
      },
      {
        "name": "V5: Rewrite + work_mem_256mb",
        "avg_ms": 17800.04,
        "rows": 67,
        "times": [
          17783.14,
          17798.91,
          17799.85,
          17801.37,
          17801.69
        ]
      },
      {
        "name": "V5: Rewrite + ssd_costs",
        "avg_ms": 10498.17,
        "rows": 67,
        "times": [
          10555.29,
          10516.48,
          10427.39,
          10428.1,
          10549.93
        ]
      },
      {
        "name": "V5: Rewrite + ssd_plus_mem",
        "avg_ms": 10766.29,
        "rows": 67,
        "times": [
          11172.16,
          11200.45,
          10503.64,
          10499.53,
          10623.08
        ]
      },
      {
        "name": "V5: Rewrite + max_parallel",
        "avg_ms": 16908.96,
        "rows": 67,
        "times": [
          16790.64,
          17154.86,
          17259.92,
          16781.37,
          16637.38
        ]
      },
      {
        "name": "V5: Rewrite + no_jit",
        "avg_ms": 18071.34,
        "rows": 67,
        "times": [
          18445.75,
          18735.17,
          18166.04,
          17561.29,
          17602.22
        ]
      },
      {
        "name": "V5: Rewrite + force_hash",
        "avg_ms": 20974.81,
        "rows": 67,
        "times": [
          20479.11,
          22541.56,
          21217.44,
          20942.33,
          20764.65
        ]
      },
      {
        "name": "V5: Rewrite + no_nestloop",
        "avg_ms": 21737.43,
        "rows": 67,
        "times": [
          21713.72,
          21681.61,
          21609.95,
          22093.37,
          21816.97
        ]
      },
      {
        "name": "V5: Rewrite + no_parallel",
        "avg_ms": 17733.63,
        "rows": 67,
        "times": [
          17863.73,
          17709.53,
          17778.72,
          17712.63,
          17673.42
        ]
      },
      {
        "name": "V5: Rewrite + no_jit+ssd",
        "avg_ms": 10322.66,
        "rows": 67,
        "times": [
          10449.02,
          10355.84,
          10125.65,
          10163.12,
          10482.38
        ]
      },
      {
        "name": "V5: Rewrite + mem_256mb+max_par",
        "avg_ms": 17021.39,
        "rows": 67,
        "times": [
          17502.35,
          16045.4,
          16302.33,
          17406.34,
          17355.51
        ]
      }
    ]
  }
}