{
  "reasoning": "Need 2+ groups with same i_item_desc, w_warehouse_name, d_week_seq. Create 2 distinct groups: Group1 (desc1, warehouse1, week1) and Group2 (desc2, warehouse2, week2). For each group, need at least 1 row meeting all filters: cs_wholesale_cost between 35-55, i_category in Children/Jewelry/Men, cd_dep_count 9-11, cd_marital_status='U', d_year=1998, hd_buy_potential='>10000', d3.d_date > d1.d_date + 3 days, inv_quantity_on_hand < cs_quantity. Also need d1.d_week_seq = d2.d_week_seq for joins. Use promotion left join so p_promo_sk can be null for some rows to get both no_promo and promo counts.",
  "tables": {
    "catalog_sales": {
      "columns": [
        "cs_item_sk",
        "cs_order_number",
        "cs_quantity",
        "cs_wholesale_cost",
        "cs_bill_cdemo_sk",
        "cs_bill_hdemo_sk",
        "cs_sold_date_sk",
        "cs_ship_date_sk",
        "cs_promo_sk"
      ],
      "rows": [
        [
          1000,
          1000,
          100,
          40.0,
          1000,
          1000,
          1000,
          1001,
          null
        ],
        [
          1001,
          1001,
          100,
          45.0,
          1001,
          1001,
          1002,
          1003,
          1000
        ]
      ]
    },
    "inventory": {
      "columns": [
        "inv_item_sk",
        "inv_warehouse_sk",
        "inv_date_sk",
        "inv_quantity_on_hand"
      ],
      "rows": [
        [
          1000,
          1000,
          1000,
          50
        ],
        [
          1001,
          1001,
          1002,
          50
        ]
      ]
    },
    "warehouse": {
      "columns": [
        "w_warehouse_sk",
        "w_warehouse_name"
      ],
      "rows": [
        [
          1000,
          "warehouse1"
        ],
        [
          1001,
          "warehouse2"
        ]
      ]
    },
    "item": {
      "columns": [
        "i_item_sk",
        "i_category",
        "i_item_desc"
      ],
      "rows": [
        [
          1000,
          "Children",
          "desc1"
        ],
        [
          1001,
          "Jewelry",
          "desc2"
        ]
      ]
    },
    "customer_demographics": {
      "columns": [
        "cd_demo_sk",
        "cd_dep_count",
        "cd_marital_status"
      ],
      "rows": [
        [
          1000,
          9,
          "U"
        ],
        [
          1001,
          10,
          "U"
        ]
      ]
    },
    "household_demographics": {
      "columns": [
        "hd_demo_sk",
        "hd_buy_potential"
      ],
      "rows": [
        [
          1000,
          ">10000"
        ],
        [
          1001,
          ">10000"
        ]
      ]
    },
    "date_dim": {
      "columns": [
        "d_date_sk",
        "d_date",
        "d_week_seq",
        "d_year"
      ],
      "rows": [
        [
          1000,
          "1998-01-01",
          1,
          1998
        ],
        [
          1001,
          "1998-01-10",
          1,
          1998
        ],
        [
          1002,
          "1998-01-01",
          2,
          1998
        ],
        [
          1003,
          "1998-01-10",
          2,
          1998
        ]
      ]
    },
    "promotion": {
      "columns": [
        "p_promo_sk"
      ],
      "rows": [
        [
          1000
        ]
      ]
    },
    "catalog_returns": {
      "columns": [
        "cr_item_sk",
        "cr_order_number"
      ],
      "rows": []
    }
  }
}